Metadata-Version: 2.1
Name: hostmydocs-client
Version: 1.0.3
Summary: Python client for HostMyDocs documentation hosting system
Home-page: https://github.com/TraceSoftwareInternational/HostMyDocs-python-client
Author: Trace Software International
Author-email: open-source@trace-software.com
License: UNKNOWN
Keywords: HostMyDocs client
Platform: UNKNOWN
Classifier: Development Status :: 5 - Production/Stable
Classifier: Intended Audience :: Developers
Classifier: Topic :: Software Development :: Build Tools
Classifier: License :: OSI Approved :: GNU General Public License v3 (GPLv3)
Classifier: Programming Language :: Python :: 3.5
Classifier: Programming Language :: Python :: 3.6
Classifier: Programming Language :: Python :: 3.7
Classifier: Programming Language :: Python :: Implementation :: PyPy
Requires-Python: >=3.5
Provides-Extra: test
